algobench/__init__.py
algobench/api_client.py
algobench/decorator.py
algobench/file_handling.py
algobench/validation.py
algobench-0.1.5.dist-info/METADATA
algobench-0.1.5.dist-info/WHEEL
algobench-0.1.5.dist-info/RECORD
