Metadata-Version: 2.4
Name: algobench
Version: 0.1.5
Summary: Supercharge your algorithm development
Author: Julius
Requires-Python: >=3.10
Requires-Dist: pydantic>=2.11.1
Requires-Dist: pytest<10.0.0,>=8.3.4
Requires-Dist: python-dotenv>=1.1.0
Requires-Dist: requests>=2.32.3
